stress_timer_oce4nm4n/__init__.py
stress_timer_oce4nm4n/__main__.py
stress_timer_oce4nm4n/main.py
stress_timer_oce4nm4n/timer.py
stress_timer-0.1.1.dist-info/METADATA
stress_timer-0.1.1.dist-info/WHEEL
stress_timer-0.1.1.dist-info/entry_points.txt
stress_timer-0.1.1.dist-info/RECORD
