Metadata-Version: 2.3
Name: stress-timer
Version: 0.1.1
Summary: A timer that says the time, and stresses you out, it also provides tracking for questions and the time spent on the questions.
License: MIT
Author: Oce4nM4n
Author-email: ayushmansihag@gmail.com
Requires-Python: >=3.10,<3.13
Classifier: Topic :: Utilities
Classifier: Environment :: MacOS X
Requires-Dist: coqui-tts (>=0.27.0,<0.28.0)
Requires-Dist: pandas (>=2.3.1,<3.0.0)
Requires-Dist: pynput (>=1.8.1,<2.0.0)
Requires-Dist: simpleaudio (>=1.0.4,<2.0.0)
